Workbook

Sheet Item Scoring
A1: Question ID | B1: Rank | C1: Retrieved Evidence ID | D1: Title | E1: Retrieved Topic | F1: Authority (S/A+/A/B+) | G1: Auto Relevance (0-2) | H1: Auto Authority (0-2) | I1: Relevance (0/1/2) | J1: Authority (0/1/2) | K1: Notes | L1: Publisher | M1: Scenario Category | N1: Expected Topic | O1: Expected Evidence IDs | P1: Question | Q1: Evidence Excerpt
A2: Q001 | B2: 1 | C2: CASE_005 | D2: 新易盛：2022年设立泰国基地，一二期已投产 | E2: 供应链布局 | F2: B+ | G2: 2 | H2: 1 | I2: 2 | J2: 1 | K2: 新易盛泰国基地一二期已投产，直接案例 | L2: 国盛证券（经腾讯新闻转载） | M2: Company Intelligence | N2: supply_chain | O2: CASE_004; CASE_005; CASE_006; CASE_008 | P2: 我们正在评估把部分产能转移到泰国。现有企业案例显示，哪些中国制造企业已经在泰国建设或扩充产能？这些案例能为海外建厂节奏提供什么参考？ | Q2: 摘要 在过去几周的周报中，我们反复强调光模块行业正处于高景气周期，AI算力需求持续爆发推动高端光模块需求快速增长，供给将成为核心矛盾。 近期我们调研发现，头部厂商在大陆和泰国加速扩产，预计2026年一季度将迎来产能集中释放，驱动业绩进入新一轮爬坡期。 【算力需求强劲，瓶颈在于供给】 算力产业链正处于高景气周期，AI模型持续创新演进推动算力需求快速增长。 业绩全面超预期： 谷歌新一代大模型Gemini 3表现优异，Scaling Law持续有效； 英伟达发布三季度财报，业绩及指引全面超预期。 谷歌与英伟达的强势表现，共同印证了模型创新与算力建设正在形成相互
A3: Q001 | B3: 2 | C3: CASE_004 | D3: 中际旭创：泰国工厂产能与国内基本齐平 | E3: 供应链布局 | F3: B+ | G3: 2 | H3: 1 | I3: 2 | J3: 1 | K3: 中际旭创泰国工厂产能与国内齐平，直接案例 | L3: 国盛证券（经腾讯新闻转载） | M3: Company Intelligence | N3: supply_chain | O3: CASE_004; CASE_005; CASE_006; CASE_008 | P3: 我们正在评估把部分产能转移到泰国。现有企业案例显示，哪些中国制造企业已经在泰国建设或扩充产能？这些案例能为海外建厂节奏提供什么参考？ | Q3: 摘要 在过去几周的周报中，我们反复强调光模块行业正处于高景气周期，AI算力需求持续爆发推动高端光模块需求快速增长，供给将成为核心矛盾。 近期我们调研发现，头部厂商在大陆和泰国加速扩产，预计2026年一季度将迎来产能集中释放，驱动业绩进入新一轮爬坡期。 【算力需求强劲，瓶颈在于供给】 算力产业链正处于高景气周期，AI模型持续创新演进推动算力需求快速增长。 业绩全面超预期： 谷歌新一代大模型Gemini 3表现优异，Scaling Law持续有效； 英伟达发布三季度财报，业绩及指引全面超预期。 谷歌与英伟达的强势表现，共同印证了模型创新与算力建设正在形成相互
A4: Q001 | B4: 3 | C4: CASE_001 | D4: Dawang Metals：客户订单转移印度后回流，企业放弃海外建厂 | E4: 供应链布局 | F4: B+ | G4: 1 | H4: 1 | I4: 1 | J4: 1 | K4: Dawang Metals 为订单转印度后回流案例，可作建厂节奏反向参照，但非泰国布局 | L4: 路透社（Reuters） | M4: Company Intelligence | N4: supply_chain | O4: CASE_004; CASE_005; CASE_006; CASE_008 | P4: 我们正在评估把部分产能转移到泰国。现有企业案例显示，哪些中国制造企业已经在泰国建设或扩充产能？这些案例能为海外建厂节奏提供什么参考？ | Q4: Evidence ID: CASE_001 Title: Dawang Metals：客户订单转移印度后回流，企业放弃海外建厂 Publisher: 路透社（Reuters） Country/Jurisdiction: CN / National Publication date: 2026-09-14 Status: CURRENT Topic: 供应链布局 Applicability scope: GENERAL Related industries: 金属铸造 Key finding: 路透原文《Companies left China to do
A5: Q001 | B5: 4 | C5: CASE_006 | D5: 天孚通信：泰国一期投产、二期2025年投入使用 | E5: 供应链布局 | F5: B+ | G5: 2 | H5: 1 | I5: 2 | J5: 1 | K5: 天孚通信泰国一期投产、二期2025启用，直接案例 | L5: 国盛证券（经腾讯新闻转载） | M5: Company Intelligence | N5: supply_chain | O5: CASE_004; CASE_005; CASE_006; CASE_008 | P5: 我们正在评估把部分产能转移到泰国。现有企业案例显示，哪些中国制造企业已经在泰国建设或扩充产能？这些案例能为海外建厂节奏提供什么参考？ | Q5: 摘要 在过去几周的周报中，我们反复强调光模块行业正处于高景气周期，AI算力需求持续爆发推动高端光模块需求快速增长，供给将成为核心矛盾。 近期我们调研发现，头部厂商在大陆和泰国加速扩产，预计2026年一季度将迎来产能集中释放，驱动业绩进入新一轮爬坡期。 【算力需求强劲，瓶颈在于供给】 算力产业链正处于高景气周期，AI模型持续创新演进推动算力需求快速增长。 业绩全面超预期： 谷歌新一代大模型Gemini 3表现优异，Scaling Law持续有效； 英伟达发布三季度财报，业绩及指引全面超预期。 谷歌与英伟达的强势表现，共同印证了模型创新与算力建设正在形成相互
A6: Q001 | B6: 5 | C6: CASE_008 | D6: 光模块厂商选择东南亚建厂以规避与欧美客户合作风险（中际旭创互动平台回复等） | E6: 供应链布局 | F6: B+ | G6: 2 | H6: 1 | I6: 2 | J6: 1 | K6: 光模块厂商东南亚建厂以规避欧美客户合作风险，直接说明泰国布局 | L6: 中国基金报 | M6: Company Intelligence | N6: supply_chain | O6: CASE_004; CASE_005; CASE_006; CASE_008 | P6: 我们正在评估把部分产能转移到泰国。现有企业案例显示，哪些中国制造企业已经在泰国建设或扩充产能？这些案例能为海外建厂节奏提供什么参考？ | Q6: 中国基金报记者 文夕 全球科技巨头持续加码算力，光模块环节厂商已成最大赢家之一。 7月14日，市值超1600亿元的全球光模块龙头中际旭创披露了一份“炸裂”的半年业绩预告。 数据显示，中际旭创预计上半年实现归母净利润21. 5亿元-25亿元，增长幅度上限超300%，而业绩下限水平甚至已可比肩去年全年。 半年业绩或超去年全年 中际旭创业绩预告显示，该公司预计上半年实现净利润21. 5亿元-25亿元，同比增长250. 3%-307. 33%。 而且，中际旭创还称，今年上半年确认股权激励费用减少公司合并净利润约9300万元。 对于上半年业绩大幅增长，中际旭创解释
A7: Q002 | B7: 1 | C7: CASE_007 | D7: 华工正源：马来西亚工厂，公开表述为规避地缘风险 | E7: 供应链布局 | F7: B+ | G7: 2 | H7: 1 | I7: 2 | J7: 1 | K7: 华工正源马来西亚工厂，公开表述为规避地缘风险，直接案例 | L7: C114通信网 | M7: Company Intelligence | N7: supply_chain | O7: CASE_007; CASE_008; CASE_010 | P7: 如果管理层想了解中国企业在马来西亚布局以降低地缘风险的公开案例，以及美国官方对马来西亚转运/原产地风险的判断，现有证据库里有哪些直接证据可参考？ | Q7: 资讯 视频 6G 光通信 物联网 量子通信 卫星互联网 数智低空 Cloud&AI 政策 运营商 设备商 终端 财经 市场 会展 直播 2026/3/25 16:29 2026十大光模块厂商，光模块厂商有哪些 C114通信网 26 1 2026年，随着 AI 算力需求持续爆发与全球数据中心带宽升级加速，光模块行业迎来“800G普及+1. 6T放量”的双轮驱动阶段。 据行业预测，2026年全球800G光模块需求量有望突破4000万只，1. 6T需求亦进入商业化元年。 在这场高速光互联的竞逐中，中国光模块厂商凭借技术突破与产能优势占据全球主导地位。 本文综合
A8: Q002 | B8: 2 | C8: CASE_010 | D8: 白宫点名东南亚为非法转运高风险地区，并推出AI执法工具 | E8: 原产地与转运 | F8: S | G8: 2 | H8: 2 | I8: 2 | J8: 2 | K8: 白宫点名东南亚（含马来西亚）为转运高风险，美国官方判断 | L8: 美国白宫（经律所解读） | M8: Company Intelligence | N8: supply_chain | O8: CASE_007; CASE_008; CASE_010 | P8: 如果管理层想了解中国企业在马来西亚布局以降低地缘风险的公开案例，以及美国官方对马来西亚转运/原产地风险的判断，现有证据库里有哪些直接证据可参考？ | Q8: Evidence ID: CASE_010 Title: 白宫点名东南亚为非法转运高风险地区，并推出AI执法工具 Publisher: 美国白宫（经律所解读） Country/Jurisdiction: US / Federal Publication date: 2026-08-13 Status: CURRENT Topic: 原产地与转运 Applicability scope: GENERAL Related industries: 通用 Key finding: 由WH_001与WH_002组成。对已在越南/泰国/马来西亚布局的企业，原产地举证
A9: Q002 | B9: 3 | C9: CASE_003 | D9: 同一反规避调查中被认定“未规避”的企业（Hanwha、Jinko马来西亚、Boviet越南） | E9: 反规避 | F9: S | G9: 0 | H9: 2 | I9: 2 | J9: 2 | K9: 美国商务部反规避认定（含马来西亚企业），直接反映美方对马来西亚原产地的官方判断 ｜ 人工判定与Auto(0)不同，请复核 | L9: 美国商务部（经律所解读） | M9: Company Intelligence | N9: supply_chain | O9: CASE_007; CASE_008; CASE_010 | P9: 如果管理层想了解中国企业在马来西亚布局以降低地缘风险的公开案例，以及美国官方对马来西亚转运/原产地风险的判断，现有证据库里有哪些直接证据可参考？ | Q9: Evidence ID: CASE_003 Title: 同一反规避调查中被认定“未规避”的企业（Hanwha、Jinko马来西亚、Boviet越南） Publisher: 美国商务部（经律所解读） Country/Jurisdiction: 马来西亚/越南 Publication date: 2023-08-18 Status: CURRENT Topic: 反规避 Applicability scope: GENERAL Related industries: 光伏 Key finding: 与CASE_002构成对照：同一规则下，供应链结构不同导致
A10: Q002 | B10: 4 | C10: CASE_002 | D10: 美国对东南亚四国光伏产品反规避认定：视为中国原产并适用对华双反 | E10: 反规避 | F10: S | G10: 0 | H10: 2 | I10: 2 | J10: 2 | K10: 美国商务部认定东南亚四国光伏视为中国原产，直接反映美方对马来西亚原产地的官方判断 ｜ 人工判定与Auto(0)不同，请复核 | L10: 美国商务部（经律所解读） | M10: Company Intelligence | N10: supply_chain | O10: CASE_007; CASE_008; CASE_010 | P10: 如果管理层想了解中国企业在马来西亚布局以降低地缘风险的公开案例，以及美国官方对马来西亚转运/原产地风险的判断，现有证据库里有哪些直接证据可参考？ | Q10: Evidence ID: CASE_002 Title: 美国对东南亚四国光伏产品反规避认定：视为中国原产并适用对华双反 Publisher: 美国商务部（经律所解读） Country/Jurisdiction: 柬埔寨/马来西亚/泰国/越南 Publication date: 2023-08-18 Status: CURRENT Topic: 反规避 Applicability scope: GENERAL Related industries: 光伏 Key finding: 2022年4月立案，2023年8月终裁。使用中国组件在东南亚完成的电池和组
A11: Q002 | B11: 5 | C11: TRD_003 | D11: 中国对越南、泰国、马来西亚出口 HS 8541/8542（中间品），2018–2025年度 | E11: 贸易流 | F11: A+ | G11: 1 | H11: 2 | I11: 1 | J11: 2 | K11: 中国对马/越/泰中间品出口数据，间接支持企业马来西亚布局判断 | L11: 联合国商品贸易统计数据库（UN Comtrade） | M11: Company Intelligence | N11: supply_chain | O11: CASE_007; CASE_008; CASE_010 | P11: 如果管理层想了解中国企业在马来西亚布局以降低地缘风险的公开案例，以及美国官方对马来西亚转运/原产地风险的判断，现有证据库里有哪些直接证据可参考？ | Q11: Evidence ID: TRD_003 Title: 中国对越南、泰国、马来西亚出口 HS 8541/8542（中间品），2018–2025年度 Publisher: 联合国商品贸易统计数据库（UN Comtrade） Country/Jurisdiction: CN / National Publication date: 持续更新 Status: CURRENT Topic: 贸易流 Applicability scope: GENERAL Related industries: ◆电子/光电 Key finding: 看东南亚产能是否依赖中国中间
A12: Q003 | B12: 1 | C12: CASE_001 | D12: Dawang Metals：客户订单转移印度后回流，企业放弃海外建厂 | E12: 供应链布局 | F12: B+ | G12: 2 | H12: 1 | I12: 2 | J12: 1 | K12: 订单转印度后回流并放弃海外建厂，直接实例 | L12: 路透社（Reuters） | M12: Company Intelligence | N12: supply_chain | O12: CASE_001; CASE_002; CASE_003 | P12: 我们想判断企业是否会因为关税规避型海外迁移效果不佳而回流中国。现有案例中有没有订单先转移海外、随后回流并放弃海外建厂的实例？ | Q12: Evidence ID: CASE_001 Title: Dawang Metals：客户订单转移印度后回流，企业放弃海外建厂 Publisher: 路透社（Reuters） Country/Jurisdiction: CN / National Publication date: 2026-09-14 Status: CURRENT Topic: 供应链布局 Applicability scope: GENERAL Related industries: 金属铸造 Key finding: 路透原文《Companies left China to do
A13: Q003 | B13: 2 | C13: CASE_008 | D13: 光模块厂商选择东南亚建厂以规避与欧美客户合作风险（中际旭创互动平台回复等） | E13: 供应链布局 | F13: B+ | G13: 1 | H13: 1 | I13: 1 | J13: 1 | K13: 东南亚建厂规避风险案例，与「回流中国」方向相反，仅作同类布局参照 | L13: 中国基金报 | M13: Company Intelligence | N13: supply_chain | O13: CASE_001; CASE_002; CASE_003 | P13: 我们想判断企业是否会因为关税规避型海外迁移效果不佳而回流中国。现有案例中有没有订单先转移海外、随后回流并放弃海外建厂的实例？ | Q13: Evidence ID: CASE_008 Title: 光模块厂商选择东南亚建厂以规避与欧美客户合作风险（中际旭创互动平台回复等） Publisher: 中国基金报 Country/Jurisdiction: CN / National Publication date: 2024-07-14 Status: CURRENT Topic: 供应链布局 Applicability scope: GENERAL Related industries: 光模块 Key finding: 文中引用中际旭创互动平台回复，可据此到互动易查原始问答，升级为一手证据。
... A201: Q040 | B201: 5 | C201: CASE_002 | D201: 美国对东南亚四国光伏产品反规避认定：视为中国原产并适用对华双反 | E201: 反规避 | F201: S | G201: 0 | H201: 2 | I201: 0 | J201: 2 | K201: 光伏反规避判例与本题三个维度的取舍无关 | L201: 美国商务部（经律所解读） | M201: Scenario Simulation Support | N201: supply_chain | O201: USMCA_001; WTO_004; WB_001 | P201: 董事会要在「保留中国产能」「迁往墨西哥」「迁往印尼」之间取舍，现有证据分别能支撑哪些关键判断（原产地门槛、本地含量要求、物流成本）？ | Q201: Evidence ID: CASE_002 Title: 美国对东南亚四国光伏产品反规避认定：视为中国原产并适用对华双反 Publisher: 美国商务部（经律所解读） Country/Jurisdiction: 柬埔寨/马来西亚/泰国/越南 Publication date: 2023-08-18 Status: CURRENT Topic: 反规避 Applicability scope: GENERAL Related industries: 光伏 Key finding: 2022年4月立案，2023年8月终裁。使用中国组件在东南亚完成的电池和组

Sheet Question Scoring
A1: Question ID | B1: Hit@5 | C1: Gold Hits in Top-5 | D1: Avg Relevance (0-2) | E1: Avg Authority (0-2) | F1: Coverage (0/1/2) | G1: Notes | H1: Scenario Category | I1: Expected Topic | J1: Question | K1: Expected Evidence IDs | L1: Top-5 Retrieved IDs
A2: Q001 | B2: 1 | C2: 4 | D2: =IFERROR(AVERAGEIF('Item Scoring'!$A$2:$A$201,$A2,'Item Scoring'!$I$2:$I$201),"") | E2: =IFERROR(AVERAGEIF('Item Scoring'!$A$2:$A$201,$A2,'Item Scoring'!$J$2:$J$201),"") | F2: 2 | G2: 泰国产能案例（CASE_004/005/006/008）全部命中，可直接回答建厂节奏 | H2: Company Intelligence | I2: supply_chain | J2: 我们正在评估把部分产能转移到泰国。现有企业案例显示，哪些中国制造企业已经在泰国建设或扩充产能？这些案例能为海外建厂节奏提供什么参考？ | K2: CASE_004; CASE_005; CASE_006; CASE_008 | L2: CASE_005; CASE_004; CASE_001; CASE_006; CASE_008
A3: Q002 | B3: 1 | C3: 2 | D3: =IFERROR(AVERAGEIF('Item Scoring'!$A$2:$A$201,$A3,'Item Scoring'!$I$2:$I$201),"") | E3: =IFERROR(AVERAGEIF('Item Scoring'!$A$2:$A$201,$A3,'Item Scoring'!$J$2:$J$201),"") | F3: 2 | G3: 马来西亚布局案例与美方对马来西亚原产地的官方判断均已覆盖（CASE_008未命中，由CASE_007/CASE_003/CASE_002覆盖） | H3: Company Intelligence | I3: supply_chain | J3: 如果管理层想了解中国企业在马来西亚布局以降低地缘风险的公开案例，以及美国官方对马来西亚转运/原产地风险的判断，现有证据库里有哪些直接证据可参考？ | K3: CASE_007; CASE_008; CASE_010 | L3: CASE_007; CASE_010; CASE_003; CASE_002; TRD_003
A4: Q003 | B4: 1 | C4: 1 | D4: =IFERROR(AVERAGEIF('Item Scoring'!$A$2:$A$201,$A4,'Item Scoring'!$I$2:$I$201),"") | E4: =IFERROR(AVERAGEIF('Item Scoring'!$A$2:$A$201,$A4,'Item Scoring'!$J$2:$J$201),"") | F4: 1 | G4: 仅 CASE_001 为直接的「回流并放弃海外建厂」实例，其余4条为东南亚扩厂案例，方向相反 | H4: Company Intelligence | I4: supply_chain | J4: 我们想判断企业是否会因为关税规避型海外迁移效果不佳而回流中国。现有案例中有没有订单先转移海外、随后回流并放弃海外建厂的实例？ | K4: CASE_001; CASE_002; CASE_003 | L4: CASE_001; CASE_008; CASE_007; CASE_004; CASE_006
A5: Q004 | B5: 1 | C5: 5 | D5: =IFERROR(AVERAGEIF('Item Scoring'!$A$2:$A$201,$A5,'Item Scoring'!$I$2:$I$201),"") | E5: =IFERROR(AVERAGEIF('Item Scoring'!$A$2:$A$201,$A5,'Item Scoring'!$J$2:$J$201),"") | F5: 2 | G5: gold 五条全部命中，布局与客户/地缘关系全覆盖 | H5: Company Intelligence | I5: supply_chain | J5: 对于计划在东南亚扩产、服务欧美客户的制造企业，现有企业案例如何说明海外工厂布局与客户合作/地缘风险之间的关系？ | K5: CASE_004; CASE_005; CASE_006; CASE_007; CASE_008 | L5: CASE_008; CASE_007; CASE_004; CASE_005; CASE_006
A6: Q005 | B6: 1 | C6: 4 | D6: =IFERROR(AVERAGEIF('Item Scoring'!$A$2:$A$201,$A6,'Item Scoring'!$I$2:$I$201),"") | E6: =IFERROR(AVERAGEIF('Item Scoring'!$A$2:$A$201,$A6,'Item Scoring'!$J$2:$J$201),"") | F6: 2 | G6: 「认定规避」与「未规避」双向判例 + 官方立场齐全 | H6: Company Intelligence | I6: trade_policy | J6: 同样在东南亚生产，为什么有的企业可能被认定为规避、有的却没有？请用现有对照案例说明供应链结构和工序布局对结果的影响。 | K6: CASE_002; CASE_003; CASE_010; DOC_001 | L6: CASE_003; CASE_002; DOC_001; DHS_001; CASE_010
A7: Q006 | B7: 1 | C7: 4 | D7: =IFERROR(AVERAGEIF('Item Scoring'!$A$2:$A$201,$A7,'Item Scoring'!$I$2:$I$201),"") | E7: =IFERROR(AVERAGEIF('Item Scoring'!$A$2:$A$201,$A7,'Item Scoring'!$J$2:$J$201),"") | F7: 2 | G7: 美方穿透规则与中方目录/暂停措施齐全 | H7: Policy / Trade Risk | I7: export_control | J7: 一家中国电池材料企业向美国客户出口含石墨、镓或锗相关物项时，2026年应重点核查哪些中国出口管制目录和暂停措施，以及美方关联企业（50%穿透）规则？ | K7: BIS_001; BIS_002; MOFCOM_001; MOFCOM_002 | L7: BIS_002; BIS_001; CASE_009; MOFCOM_002; MOFCOM_001
A8: Q007 | B8: 1 | C8: 4 | D8: =IFERROR(AVERAGEIF('Item Scoring'!$A$2:$A$201,$A8,'Item Scoring'!$I$2:$I$201),"") | E8: =IFERROR(AVERAGEIF('Item Scoring'!$A$2:$A$201,$A8,'Item Scoring'!$J$2:$J$201),"") | F8: 2 | G8: 规则、暂停期、筛查清单齐全 | H8: Policy / Trade Risk | I8: export_control | J8: 美国客户的母公司或关联公司被列入Entity List或MEU List时，我们应如何判断50%持股穿透规则是否会影响交易？当前暂停期又如何改变时间判断？ | K8: BIS_001; BIS_002; CASE_009; ITA_001 | L8: CASE_009; BIS_001; BIS_002; ITA_001; DHS_001
A9: Q008 | B9: 1 | C9: 3 | D9: =IFERROR(AVERAGEIF('Item Scoring'!$A$2:$A$201,$A9,'Item Scoring'!$I$2:$I$201),"") | E9: =IFERROR(AVERAGEIF('Item Scoring'!$A$2:$A$201,$A9,'Item Scoring'!$J$2:$J$201),"") | F9: 2 | G9: 暂停期与恢复规则齐全；FR_001未命中但由BIS_001/002覆盖 | H9: Policy / Trade Risk | I9: export_control | J9: 我们准备在2026年11月前后签署一份对美长期供货合同。BIS关联企业规则的暂停与恢复时间线会带来什么合规窗口风险？ | K9: BIS_001; BIS_002; CASE_009; FR_001 | L9: BIS_002; CASE_009; BIS_001; MOFCOM_002; NIO_001
A10: Q009 | B10: 1 | C10: 4 | D10: =IFERROR(AVERAGEIF('Item Scoring'!$A$2:$A$201,$A10,'Item Scoring'!$I$2:$I$201),"") | E10: =IFERROR(AVERAGEIF('Item Scoring'!$A$2:$A$201,$A10,'Item Scoring'!$J$2:$J$201),"") | F10: 2 | G10: 政策方向、行政令与执法先例齐全 | H10: Policy / Trade Risk | I10: trade_policy | J10: 公司计划通过越南、泰国或马来西亚完成部分加工后出口美国。美国当前对非法转运和原产地执法的政策方向会带来哪些额外风险？ | K10: WH_001; WH_002; CASE_010; CSIS_001 | L10: CASE_010; WH_002; WH_001; CASE_002; CSIS_001
A11: Q010 | B11: 1 | C11: 3 | D11: =IFERROR(AVERAGEIF('Item Scoring'!$A$2:$A$201,$A11,'Item Scoring'!$I$2:$I$201),"") | E11: =IFERROR(AVERAGEIF('Item Scoring'!$A$2:$A$201,$A11,'Item Scoring'!$J$2:$J$201),"") | F11: 2 | G11: 「认定规避」判例与美方执法立场齐全（CASE_003/DOC_001未命中，由CASE_002/WH_002替代） | H11: Policy / Trade Risk | I11: trade_policy | J11: 如果我们想用历史执法案例评估‘在东南亚加工就能改变原产地并避开美国贸易救济措施’这一假设，现有证据支持什么判断？ | K11: CASE_002; CASE_003; CASE_010; DOC_001; WH_002 | L11: CASE_002; CASE_010; DHS_001; WH_001; WH_002
A12: Q011 | B12: 1 | C12: 3 | D12: =IFERROR(AVERAGEIF('Item Scoring'!$A$2:$A$201,$A12,'Item Scoring'!$I$2:$I$201),"") | E12: =IFERROR(AVERAGEIF('Item Scoring'!$A$2:$A$201,$A12,'Item Scoring'!$J$2:$J$201),"") | F12: 2 | G12: 中国官方规则 + IMF/UNCTAD 国际投资环境证据齐全 | H12: Policy / Trade Risk | I12: investment_policy | J12: 一家中国制造企业计划新建海外工厂。2026年中国对外投资制度中有哪些官方规则、以及哪些国际投资环境证据，应纳入项目立项和合规评估？ | K12: CNGOV_001; IMF_001; UNCTAD_001 | L12: CNGOV_001; IMF_001; UNCTAD_001; CASE_001; DHS_001
A13: Q012 | B13: 1 | C13: 2 | D13: =IFERROR(AVERAGEIF('Item Scoring'!$A$2:$A$201,$A13,'Item Scoring'!$I$2:$I$201),"") | E13: =IFERROR(AVERAGEIF('Item Scoring'!$A$2:$A$201,$A13,'Item Scoring'!$J$2:$J$201),"") | F13: 1 | G13: 仅 WEF/UNCTAD 命中，缺 IMF 碎片化框架与麦肯锡情景证据 | H13: Policy / Trade Risk | I13: investment_policy | J13: 管理层需要判断地缘经济碎片化是否会持续影响跨境投资决策。哪些国际组织证据可以支持这一政策/投资风险判断？ | K13: IMF_001; MCK_001; UNCTAD_001; WEF_001 | L13: WTO_002; WEF_001; UNCTAD_001; CNGOV_001; WTO_004
... A41: Q040 | B41: 1 | C41: 3 | D41: =IFERROR(AVERAGEIF('Item Scoring'!$A$2:$A$201,$A41,'Item Scoring'!$I$2:$I$201),"") | E41: =IFERROR(AVERAGEIF('Item Scoring'!$A$2:$A$201,$A41,'Item Scoring'!$J$2:$J$201),"") | F41: 2 | G41: 三份 gold（USMCA_001/WB_001/WTO_004）全部命中，三个维度均有直接证据 | H41: Scenario Simulation Support | I41: supply_chain | J41: 董事会要在「保留中国产能」「迁往墨西哥」「迁往印尼」之间取舍，现有证据分别能支撑哪些关键判断（原产地门槛、本地含量要求、物流成本）？ | K41: USMCA_001; WTO_004; WB_001 | L41: USMCA_001; WB_001; IRS_001; WTO_004; CASE_002

Sheet Summary
A1: Task 2 — Human Evaluation Summary | B1: Value | C1: Target | D1: Status
A2: Questions | B2: 30 | C2: 30 questions
A4: Primary metrics (auto-calculated from Question Scoring)
A5: Avg Relevance (Top-5, 0-2) | B5: =AVERAGE('Question Scoring'!$D$2:$D$41) | C5: >= 1.5 | D5: =IF(B5="","",IF(B5>=1.5,"PASS","FAIL"))
A6: Avg Authority (Top-5, 0-2) | B6: =AVERAGE('Question Scoring'!$E$2:$E$41) | C6: >= 1.5 | D6: =IF(B6="","",IF(B6>=1.5,"PASS","FAIL"))
A7: Hit@5 rate (>=1 correct evidence in Top-5) | B7: =AVERAGE('Question Scoring'!$B$2:$B$41) | C7: >= 80% | D7: =IF(B7="","",IF(B7>=0.8,"PASS","FAIL"))
A8: Avg Coverage (0-2) | B8: =IFERROR(AVERAGE('Question Scoring'!$F$2:$F$41),"") | C8: report | D8: report only
A10: Note | B10: Fill the yellow cells first — Summary updates automatically.
A12: Scoring pass | B12: AI-assisted pre-scoring (content-based, keyed by evidence_id). Review flagged rows before finalising.

Sheet Rubric
A1: Dimension | B1: Score | C1: Definition
A2: Relevance | B2: 2 | C2: Retrieved evidence directly answers / directly supports the question. (Usually: it is in Expected Evidence IDs.)
A3: Relevance | B3: 1 | C3: Partially relevant — same topic bucket, usable as supporting context but not a direct answer.
A4: Relevance | B4: 0 | C4: Irrelevant to the question.
A5: Authority | B5: 2 | C5: S / A+ / A source — government regulation, official company filing, WTO/UN/World Bank, IMF, CSIS, McKinsey, industry association.
A6: Authority | B6: 1 | C6: B+ source — consulting reports, market research, brokerage / media summaries.
A7: Authority | B7: 0 | C7: Low-quality or unverifiable source.
A8: Coverage | B8: 2 | C8: Retrieval found enough evidence to answer the question end-to-end.
A9: Coverage | B9: 1 | C9: Partial — some but not all facets covered.
A10: Coverage | B10: 0 | C10: No usable supporting evidence retrieved.
A12: How to score | C12: Score every retrieved item in 'Item Scoring' (yellow cells). Then give one Coverage score and Notes per question in 'Question Scoring'.
A13: Auto columns | C13: Auto Relevance = 2 if the item is in Expected Evidence IDs, 1 if its topic is in the question's topic bucket, else 0. Auto Authority = 2 for S/A+/A, 1 for B+/B.
